pcli/__init__.py
pcli/main.py
pcli/util.py
pcli/controllers/__init__.py
pcli/controllers/base.py
pcli/controllers/config.py
pcli/controllers/instancetypes.py
pcli/controllers/job.py
pcli/core/__init__.py
pcli/core/exc.py
pcli/core/perian.py
pcli/core/version.py
pcli/ext/__init__.py
pcli/ext/db.py
pcli/plugins/__init__.py
pcli/templates/__init__.py
pcli/templates/job.jinja2
periancli-0.0.26.dist-info/LICENSE.md
periancli-0.0.26.dist-info/METADATA
periancli-0.0.26.dist-info/WHEEL
periancli-0.0.26.dist-info/entry_points.txt
periancli-0.0.26.dist-info/top_level.txt
periancli-0.0.26.dist-info/RECORD
