Metadata-Version: 2.1
Name: periancli
Version: 0.0.26
Summary: Perian Sky Job Platform CLI
Home-page: https://perian.io
Author: Perian
Author-email: info@perian.io
License: unlicensed
License-File: LICENSE.md
Requires-Dist: cement (==3.0.8)
Requires-Dist: jinja2 (==3.1.2)
Requires-Dist: pyyaml (==6.0.1)
Requires-Dist: colorlog (==6.7.0)
Requires-Dist: rich (==13.4.2)
Requires-Dist: perian (==0.1.23)
